aclustermap/__init__.py
aclustermap/__main__.py
aclustermap/default_format.yaml
aclustermap/pandas.DataFrame4
aclustermap-0.1.7.dist-info/LICENSE
aclustermap-0.1.7.dist-info/METADATA
aclustermap-0.1.7.dist-info/WHEEL
aclustermap-0.1.7.dist-info/entry_points.txt
aclustermap-0.1.7.dist-info/RECORD
