Metadata-Version: 2.1
Name: aclustermap
Version: 0.1.7
Summary: Convert YAMLized pandas DataFrame to Seaborn clustermap
License: MIT
Author: Ben Skubi
Author-email: skubi@ohsu.edu
Requires-Python: >=3.12,<4.0
Classifier: License :: OSI Approved :: MIT License
Classifier: Programming Language :: Python :: 3
Classifier: Programming Language :: Python :: 3.12
Requires-Dist: PyYAML (>=6.0.1,<7.0.0)
Requires-Dist: colorcet (>=3.0.1,<4.0.0)
Requires-Dist: seaborn (>=0.13.2,<0.14.0)
